rudp/__init__.py
rudp/udpreceiver.py
rudp/udpsender.py
rudp-1.0.3.dist-info/LICENSE
rudp-1.0.3.dist-info/METADATA
rudp-1.0.3.dist-info/WHEEL
rudp-1.0.3.dist-info/top_level.txt
rudp-1.0.3.dist-info/RECORD
