Metadata-Version: 2.1
Name: rudp
Version: 1.0.3
Summary: Send and receive message simply by UDP.
Home-page: https://github.com/reeve0930/rudp
Author: reeve0930
Author-email: reeve0930@gmail.com
License: MIT
Keywords: rudp RUDP UDP socket
Platform: UNKNOWN
Classifier: License :: OSI Approved :: MIT License
Classifier: Programming Language :: Python :: 3.7
